burner_process/__init__.py
burner_process/_burner_process.py
burner_process/_worker.py
burner_process-1.0.1.dist-info/LICENSE.txt
burner_process-1.0.1.dist-info/METADATA
burner_process-1.0.1.dist-info/WHEEL
burner_process-1.0.1.dist-info/top_level.txt
burner_process-1.0.1.dist-info/RECORD
