Metadata-Version: 2.1
Name: burner-process
Version: 1.0.1
Summary: A wrapper that runs a function inside a new process, that is not a child of the main process.
Home-page: https://github.com/benvigano/burner_process
Author: benvigano
Author-email: beniamino.vigano@protonmail.com
License: MIT
Keywords: subprocessing,subprocess,process,multiprocessing,processify,processifier,memory leak
License-File: LICENSE.txt
